{
  "commit": "2ca013935e67b5fdd607a9cc400d01a9674ae2bf",
  "generated": "2025-01-30T09:32:23.696Z",
  "metadata": [
    {
      "__outstatic": {
        "commit": "006b7ac08350a992cf7a4657c47fe448c302874a",
        "hash": "174189173",
        "path": "outstatic/content/docs/hiring-manager-demo.md"
      },
      "author": {
        "name": "",
        "picture": "https://avatars.githubusercontent.com/u/168521089?v=4"
      },
      "collection": "docs",
      "coverImage": "",
      "description": "",
      "publishedAt": "2025-01-29T11:30:54.238Z",
      "slug": "hiring-manager-demo",
      "status": "published",
      "title": "Hiring Manager Demo"
    },
    {
      "__outstatic": {
        "commit": "7d11805390acf982e01af693251bbc8781027032",
        "hash": "3325373559",
        "path": "outstatic/content/docs/hirequotient-new-docs.md"
      },
      "author": {
        "name": "",
        "picture": "https://avatars.githubusercontent.com/u/168521089?v=4"
      },
      "collection": "docs",
      "coverImage": "",
      "description": "",
      "publishedAt": "2025-01-29T12:31:29.853Z",
      "slug": "hirequotient-new-docs",
      "status": "published",
      "title": "HireQuotient new docs"
    },
    {
      "__outstatic": {
        "commit": "df4808ef9a72f86d9507a14d1da28c3545010ea8",
        "hash": "2894071242",
        "path": "outstatic/content/docs/introduction.md"
      },
      "author": {
        "name": "Andre Vitorio",
        "picture": "https://avatars.githubusercontent.com/u/1417109?v=4"
      },
      "collection": "docs",
      "coverImage": "",
      "description": "",
      "publishedAt": "2023-05-26T17:50:55.000Z",
      "slug": "introduction",
      "status": "published",
      "title": "Introduction"
    },
    {
      "__outstatic": {
        "commit": "65ab551e11ff454c4aa1f6bbbddeec41437df70f",
        "hash": "2214291809",
        "path": "outstatic/content/docs/demo.md"
      },
      "author": {
        "name": "",
        "picture": "https://avatars.githubusercontent.com/u/168521089?v=4"
      },
      "collection": "docs",
      "coverImage": "",
      "description": "",
      "publishedAt": "2025-01-30T10:01:21.883Z",
      "slug": "demo",
      "status": "published",
      "title": "Demo"
    },
    {
      "__outstatic": {
        "commit": "2ca013935e67b5fdd607a9cc400d01a9674ae2bf",
        "hash": "1667361230",
        "path": "outstatic/content/menus/docs-menu.md"
      },
      "author": {
        "name": "Andre Vitorio",
        "picture": "https://avatars.githubusercontent.com/u/1417109?v=4"
      },
      "collection": "menus",
      "coverImage": "",
      "description": "",
      "publishedAt": "2025-01-30T15:18:37.000Z",
      "slug": "docs-menu",
      "status": "published",
      "title": "Docs Menu"
    }
  ]
}